sayvai_tools/__init__.py
sayvai_tools/tools/__init__.py
sayvai_tools/tools/audio/__init__.py
sayvai_tools/tools/audio/streaming.py
sayvai_tools/tools/calendar/__init__.py
sayvai_tools/tools/calendar/tool.py
sayvai_tools/tools/calendar/calendar/__init__.py
sayvai_tools/tools/calendar/calendar/tool.py
sayvai_tools/tools/calendar/calendar_sql/__init__.py
sayvai_tools/tools/calendar/calendar_sql/tool.py
sayvai_tools/tools/calendar_block/__init__.py
sayvai_tools/tools/calendar_block/tool.py
sayvai_tools/tools/conversational_human/__init__.py
sayvai_tools/tools/conversational_human/iohuman.py
sayvai_tools/tools/date/__init__.py
sayvai_tools/tools/date/tool.py
sayvai_tools/tools/display_events/__init__.py
sayvai_tools/tools/display_events/tool.py
sayvai_tools/tools/forms/__init__.py
sayvai_tools/tools/forms/tool.py
sayvai_tools/tools/retrive_email/__init__.py
sayvai_tools/tools/retrive_email/tool.py
sayvai_tools/tools/retrive_phone/__init__.py
sayvai_tools/tools/retrive_phone/tool.py
sayvai_tools/tools/send_mail/__init__.py
sayvai_tools/tools/send_mail/tool.py
sayvai_tools/tools/spreadsheets/__init__.py
sayvai_tools/tools/spreadsheets/gsheets/__init__.py
sayvai_tools/tools/spreadsheets/gsheets/tool.py
sayvai_tools/tools/spreadsheets/sql_sheets/__init__.py
sayvai_tools/tools/spreadsheets/sql_sheets/tool.py
sayvai_tools/tools/sql_database/__init__.py
sayvai_tools/tools/sql_database/prompt.py
sayvai_tools/tools/sql_database/tool.py
sayvai_tools/tools/vectordb/__init__.py
sayvai_tools/tools/vectordb/chromadb/__init__.py
sayvai_tools/tools/vectordb/chromadb/tool.py
sayvai_tools/tools/vectordb/pgvector/__init__.py
sayvai_tools/tools/vectordb/pgvector/tool.py
sayvai_tools/tools/vectordb/pinecone/__init__.py
sayvai_tools/tools/vectordb/pinecone/tool.py
sayvai_tools/utils/__init__.py
sayvai_tools/utils/database/__init__.py
sayvai_tools/utils/database/dbbase.py
sayvai_tools/utils/database/dbchain.py
sayvai_tools/utils/google/__init__.py
sayvai_tools/utils/google/forms.py
sayvai_tools-0.0.2.dist-info/METADATA
sayvai_tools-0.0.2.dist-info/WHEEL
sayvai_tools-0.0.2.dist-info/top_level.txt
sayvai_tools-0.0.2.dist-info/RECORD
