Metadata-Version: 2.1
Name: sayvai-tools
Version: 0.0.2
Summary: Tools for the assistant
Author: sayvai-io
Requires-Dist: langchain
Requires-Dist: langchain-experimental
Requires-Dist: google-api-python-client
Requires-Dist: openai
Requires-Dist: tiktoken
Requires-Dist: SQLAlchemy
Requires-Dist: elevenlabs (==0.2.24)
Requires-Dist: google-auth-oauthlib
Requires-Dist: google-auth-httplib2
Requires-Dist: numpy
Requires-Dist: google
Requires-Dist: google-cloud-speech
Requires-Dist: cloud-sql-python-connector
Requires-Dist: pg8000
Requires-Dist: pinecone-client
Requires-Dist: pgvector
Requires-Dist: pandas
Requires-Dist: openpyxl
Requires-Dist: gspread (==5.11.3)
Requires-Dist: pyaudio
Requires-Dist: pydub
Requires-Dist: oauth2client
Provides-Extra: dev
Requires-Dist: pytest ; extra == 'dev'
Requires-Dist: pylint ; extra == 'dev'
